intersectionalipy/__init__.py
intersectionalipy/intersectionalipy.py
intersectionalipy-0.1.1.dist-info/LICENSE
intersectionalipy-0.1.1.dist-info/METADATA
intersectionalipy-0.1.1.dist-info/WHEEL
intersectionalipy-0.1.1.dist-info/top_level.txt
intersectionalipy-0.1.1.dist-info/RECORD
