Metadata-Version: 2.1
Name: intersectionalipy
Version: 0.1.1
Summary: A package for simplifying intersectional analysis
Home-page: https://github.com/intersectionalipy/intersectionalipy
Author: Intersectionalipy
Author-email: intersectionalipy@protonmail.com
License: UNKNOWN
Platform: UNKNOWN
Classifier: Programming Language :: Python :: 3
Classifier: License :: OSI Approved :: MIT License
Classifier: Operating System :: OS Independent
Requires-Python: >=3.9
License-File: LICENSE
